d_imm/__init__.py
d_imm/imm_model.py
d_imm/histogram/__init__.py
d_imm/histogram/histogram.py
d_imm/splitters/__init__.py
d_imm/splitters/cut_finder.cp311-win_amd64.pyd
d_imm/splitters/setup.py
distributed_imm-0.4.1.dist-info/LICENSE
distributed_imm-0.4.1.dist-info/METADATA
distributed_imm-0.4.1.dist-info/WHEEL
distributed_imm-0.4.1.dist-info/top_level.txt
distributed_imm-0.4.1.dist-info/RECORD
