Metadata-Version: 2.1
Name: distributed-imm
Version: 0.4.1
Summary: A distributed implementation of Iterative Mistake Minimization (IMM) for clustering explanations
Home-page: https://github.com/ScalableXplain/distributed_imm
Author: Saadha
Author-email: marium.20@cse.mrt.ac.lk
License: MIT
Classifier: Programming Language :: Python :: 3
Classifier: License :: OSI Approved :: MIT License
Classifier: Operating System :: OS Independent
Requires-Python: >=3.7
License-File: LICENSE
Requires-Dist: numpy
Requires-Dist: pyspark
Requires-Dist: cython
Requires-Dist: graphviz
Requires-Dist: pandas
